pyganalytics/__init__.py
pyganalytics/exceptions.py
pyganalytics/api/__init__.py
pyganalytics/api/authorization.py
pyganalytics/api/client.py
pyganalytics/api/reporting.py
pyganalytics/core/__init__.py
pyganalytics/core/iterator.py
pyganalytics/core/properties.py
pyganalytics/core/report.py
pyganalytics/core/requests.py
pyganalytics/utility/__init__.py
pyganalytics/utility/dateranges.py
pyganalytics/utility/enums.py
pyganalytics_reporting-0.2.0.dist-info/METADATA
pyganalytics_reporting-0.2.0.dist-info/RECORD
pyganalytics_reporting-0.2.0.dist-info/WHEEL
pyganalytics_reporting-0.2.0.dist-info/top_level.txt
