Metadata-Version: 2.1
Name: pyganalytics-reporting
Version: 0.2.0
Summary: A python wrapper for the Google Analytics Reporting API v4
Home-page: https://github.com/Kordishal/pyganalytics-reporting
Author: Jonas Waeber
Author-email: jonaswaeber@gmail.com
License: MIT
Platform: UNKNOWN
Classifier: Programming Language :: Python :: 3
Classifier: Programming Language :: Python :: 3.7
Classifier: License :: OSI Approved :: MIT License
Classifier: Operating System :: OS Independent
Classifier: Development Status :: 3 - Alpha
Classifier: Intended Audience :: Developers
Classifier: Intended Audience :: End Users/Desktop
Classifier: Intended Audience :: Science/Research
Classifier: Topic :: Software Development :: Libraries :: Python Modules
Requires-Dist: google-api-python-client
Requires-Dist: google-auth-oauthlib
Requires-Dist: isodate
Requires-Dist: python-dateutil
